README.txt
setup.py
OpenplansBoot.egg-info/PKG-INFO
OpenplansBoot.egg-info/SOURCES.txt
OpenplansBoot.egg-info/dependency_links.txt
OpenplansBoot.egg-info/entry_points.txt
OpenplansBoot.egg-info/not-zip-safe
OpenplansBoot.egg-info/requires.txt
OpenplansBoot.egg-info/top_level.txt
doc/CHANGES.txt
openplansboot/__init__.py
openplansboot/apacheconf.template
openplansboot/newbuild.sh.template
openplansboot/newsite.ini.example
openplansboot/newsite.py
