Metadata-Version: 1.0
Name: OpenplansBoot
Version: 0.2
Summary: Creates new Openplans site deployment setup
Home-page: http://www.openplans.org/projects/opencore
Author: TOPP
Author-email: info@openplans.org
License: GPLv3
Keywords: TOPP openplans opencore open planning project openplans.org
Platform: UNKNOWN
